colcon_spawn_shell/__init__.py
colcon_spawn_shell/spawn_shell.py
colcon_spawn_shell/template/__init__.py
colcon_spawn_shell/template/spawn_shell.bash.em
colcon_spawn_shell-0.3.0.dist-info/LICENSE.txt
colcon_spawn_shell-0.3.0.dist-info/METADATA
colcon_spawn_shell-0.3.0.dist-info/WHEEL
colcon_spawn_shell-0.3.0.dist-info/entry_points.txt
colcon_spawn_shell-0.3.0.dist-info/top_level.txt
colcon_spawn_shell-0.3.0.dist-info/RECORD
