Metadata-Version: 2.1
Name: colcon-spawn-shell
Version: 0.3.0
Summary: Source colcon workspaces in a new shell.
Home-page: http://github.com/colcon/colcon-spawn-shell
Author: Shane Loretz
Author-email: shane.loretz@gmail.com
Maintainer: Shane Loretz
Maintainer-email: shane.loretz@gmail.com
License: Apache License, Version 2.0
Download-URL: https://github.com/colcon/colcon-spawn-shell/archive/0.3.0.tar.gz
Platform: UNKNOWN
Classifier: Development Status :: 3 - Alpha
Classifier: Environment :: Plugins
Classifier: Intended Audience :: Developers
Classifier: License :: OSI Approved :: Apache Software License
Classifier: Operating System :: POSIX
Classifier: Programming Language :: Python :: 3
Classifier: Programming Language :: Python :: 3.5
Classifier: Topic :: Software Development :: Build Tools
Requires-Python: >=3.6
License-File: LICENSE.txt
Requires-Dist: colcon-core (>=0.12.0)
Requires-Dist: colcon-bash (>=0.3.0)
Provides-Extra: test
Requires-Dist: pytest ; extra == 'test'
Requires-Dist: scspell3k (>=2.2) ; extra == 'test'
